LICENSE
MANIFEST.in
README.rst
setup.py
jailconf/__init__.py
jailconf/exceptions.py
jailconf/lexer.py
jailconf/parser.py
jailconf/structures.py
jailconf.egg-info/PKG-INFO
jailconf.egg-info/SOURCES.txt
jailconf.egg-info/dependency_links.txt
jailconf.egg-info/requires.txt
jailconf.egg-info/top_level.txt