Metadata-Version: 1.2
Name: jailconf
Version: 0.2.2
Summary: Parse and edit your FreeBSD jail.conf file
Home-page: https://github.com/leforestier/jailconf
Author: Benjamin Le Forestier
Author-email: benjamin@leforestier.org
License: UNKNOWN
Keywords: jail.conf,parse,edit,configuration,freebsd,jail
Platform: UNKNOWN
Classifier: Intended Audience :: Developers
Classifier: Intended Audience :: System Administrators
Classifier: License :: OSI Approved :: BSD License
Classifier: Operating System :: OS Independent
Classifier: Programming Language :: Python
Classifier: Programming Language :: Python :: 3
Classifier: Programming Language :: Python :: 3.3
Classifier: Programming Language :: Python :: 3.4
Classifier: Programming Language :: Python :: 3.5
Classifier: Programming Language :: Python :: 3.6
Classifier: Topic :: System :: Systems Administration
Classifier: Topic :: Software Development :: Libraries :: Python Modules
Requires-Python: >=3.0
